rapidearth/__init__.py
rapidearth/__main__.py
rapidearth-0.1.1.dist-info/LICENSE
rapidearth-0.1.1.dist-info/METADATA
rapidearth-0.1.1.dist-info/WHEEL
rapidearth-0.1.1.dist-info/top_level.txt
rapidearth-0.1.1.dist-info/RECORD
