Metadata-Version: 2.1
Name: rapidearth
Version: 0.1.1
Summary: A novel search engine for finding rare objects in satellite imagery
Home-page: https://github.com/cluel01/rapidearth
Author: Christian Luelf
Author-email: christian.luelf@uni-muenster.de
License: GNU GENERAL PUBLIC LICENSE Version 3
Platform: UNKNOWN
Classifier: Development Status :: 2 - Pre-Alpha
Classifier: License :: OSI Approved :: GNU General Public License v3 (GPLv3)
Classifier: Programming Language :: Python
Classifier: Programming Language :: Python :: 2
Classifier: Programming Language :: Python :: 2.7
Classifier: Programming Language :: Python :: 3
Classifier: Programming Language :: Python :: 3.4
Classifier: Programming Language :: Python :: 3.5
Classifier: Programming Language :: Python :: 3.6
Classifier: Programming Language :: Python :: 3.7
